nrel_dev_api/__init__.py
nrel_dev_api/_core.py
nrel_dev_api/_nbdev.py
nrel_dev_api/solar/__init__.py
nrel_dev_api/solar/dataset_query.py
nrel_dev_api/solar/nsrdb.py
nrel_dev_api/solar/pvwatts_v6.py
nrel_dev_api/solar/resource_data.py
nrel_dev_api-0.1.1.dist-info/LICENSE
nrel_dev_api-0.1.1.dist-info/METADATA
nrel_dev_api-0.1.1.dist-info/WHEEL
nrel_dev_api-0.1.1.dist-info/entry_points.txt
nrel_dev_api-0.1.1.dist-info/top_level.txt
nrel_dev_api-0.1.1.dist-info/RECORD
