Metadata-Version: 2.1
Name: nrel_dev_api
Version: 0.1.1
Summary: Access data and analysis services that NREL (National Renewable Energy Lab) provides using a Python API.
Home-page: https://github.com/sarthakjariwala/nrel_dev_api/tree/master/
Author: Sarthak Jariwala
Author-email: jariwala@uw.edu
License: Apache Software License 2.0
Keywords: NREL
Platform: UNKNOWN
Classifier: Development Status :: 3 - Alpha
Classifier: Intended Audience :: Developers
Classifier: License :: OSI Approved :: Apache Software License
Classifier: Natural Language :: English
Classifier: Programming Language :: Python :: 3.6
Classifier: Programming Language :: Python :: 3.7
Classifier: Programming Language :: Python :: 3.8
Requires-Python: >=3.6
